{
  "mlb": [
    {
      "title": "Cleveland Guardians vs New York Yankees",
      "channel": "2798",
      "stream": null
    },
    {
      "title": "Toronto Blue Jays vs Atlanta Braves",
      "channel": "2799",
      "stream": null
    },
    {
      "title": "Chicago White Sox vs Minnesota Twins",
      "channel": "2800",
      "stream": null
    },
    {
      "title": "San Francisco Giants vs Milwaukee Brewers",
      "channel": "2801",
      "stream": null
    },
    {
      "title": "Texas Rangers vs St. Louis Cardinals",
      "channel": "2802",
      "stream": null
    },
    {
      "title": "Athletics vs Chicago Cubs",
      "channel": "2803",
      "stream": null
    },
    {
      "title": "Pittsburgh Pirates vs Houston Astros",
      "channel": "2804",
      "stream": null
    },
    {
      "title": "Colorado Rockies vs Los Angeles Angels",
      "channel": "2805",
      "stream": null
    },
    {
      "title": "New York Mets vs Seattle Mariners",
      "channel": "2806",
      "stream": null
    },
    {
      "title": "Los Angeles Dodgers vs Arizona Diamondbacks",
      "channel": "2807",
      "stream": null
    }
  ],
  "nba": [],
  "soccer": [],
  "nhl": [
    {
      "title": "Vegas Golden Knights vs Carolina Hurricanes",
      "channel": "2793",
      "stream": null
    }
  ],
  "nfl": []
}